README.md
setup.py
src/dpc/__init__.py
src/dpc/consumer.py
src/dpc/producer.py
src/dpc/base/__init__.py
src/dpc/base/consumer.py
src/dpc/base/producer.py
src/dpc/protos/__init__.py
src/dpc/protos/kafkapixy_pb2.py
src/dpc/protos/kafkapixy_pb2_grpc.py
src/dpc/tools/__init__.py
src/dpc/tools/utils.py
src/rflow_dpc.egg-info/PKG-INFO
src/rflow_dpc.egg-info/SOURCES.txt
src/rflow_dpc.egg-info/dependency_links.txt
src/rflow_dpc.egg-info/requires.txt
src/rflow_dpc.egg-info/top_level.txt