Metadata-Version: 2.1
Name: rflow-dpc
Version: 0.0.1
Summary: Rflow Data Producer and Consumer
Home-page: UNKNOWN
Author: LI, FUU
Author-email: rflowteam@rakuten.com
License: UNKNOWN
Platform: UNKNOWN
